LICENSE
MANIFEST.in
README.md
pyproject.toml
setup.cfg
setup.py
jw_nx/__init__.py
jw_nx/asgi.py
jw_nx/auth.py
jw_nx/backends.py
jw_nx/exceptions.py
jw_nx/serializers.py
jw_nx/settings.py
jw_nx/tokens.py
jw_nx/urls.py
jw_nx/utils.py
jw_nx/views.py
jw_nx/wsgi.py
jw_nx.egg-info/PKG-INFO
jw_nx.egg-info/SOURCES.txt
jw_nx.egg-info/dependency_links.txt
jw_nx.egg-info/requires.txt
jw_nx.egg-info/top_level.txt
tests/__init__.py
tests/base.py
tests/conftest.py
tests/test_admin.py
tests/test_features.py
tests/test_views.py
tests/urls.py